setup.py
bin/nephelo
nephelo/__init__.py
nephelo/compilescripts.py
nephelo/compute.py
nephelo/config.py
nephelo/delete.py
nephelo/deploy.py
nephelo/network.py
nephelo/segments.py
nephelo/template_generator.py
nephelo.egg-info/PKG-INFO
nephelo.egg-info/SOURCES.txt
nephelo.egg-info/dependency_links.txt
nephelo.egg-info/not-zip-safe
nephelo.egg-info/requires.txt
nephelo.egg-info/top_level.txt
nephelo/templates/subnet.json
nephelo/templates/vpc.json