Metadata-Version: 1.0
Name: nephelo
Version: 0.106
Summary: A Cloud Formation library to more easily. Nephelo, short for Nephelococcygia, is the art of watching clouds.
Home-page: https://github.com/tamme-io/nephelo
Author: tamme
Author-email: opensource@tamme.io
License: MIT
Platform: UNKNOWN
